{"cameraMode":{"drawMode":0,"name":"Shaded","section":"Shading Mode"},"sceneLighting":false,"audioPlay":false,"sceneViewState":{"showFog":true,"showMaterialUpdate":false,"showSkybox":false,"showFlares":true,"showImageEffects":true,"showParticleSystems":true},"in2DMode":false,"pivot":{"x":-36.677947998046878,"y":-3.345562696456909,"z":63.32439422607422},"rotation":{"x":-0.10371718555688858,"y":-0.8219910264015198,"z":0.15878577530384065,"w":-0.5370340347290039},"size":11.397480964660645,"orthographic":false}